thorsky/__init__.py
thorsky/cartesian_bright.dat
thorsky/observatories_rev.dat
thorsky/thorskyclasses3.py
thorsky/thorskyutil.py
thorsky-1.1.data/scripts/pyskycalc3.py
thorsky-1.1.dist-info/LICENSE
thorsky-1.1.dist-info/METADATA
thorsky-1.1.dist-info/WHEEL
thorsky-1.1.dist-info/top_level.txt
thorsky-1.1.dist-info/RECORD
