Metadata-Version: 1.0
Name: thorsky
Version: 1.1
Summary: Python based skycalc GUI
Home-page: http://www.dartmouth.edu
Author: John Thorstensen
Author-email: John.Thorstensen@dartmouth.edu
License: BSD 2-Clause License
Platform: UNKNOWN
